gerald_tools/__init__.py
gerald_tools/dataset.py
gerald_tools/utils/__init__.py
gerald_tools/utils/labels.py
gerald_tools/utils/tools.py
gerald_tools/utils/transforms.py
gerald_tools-0.1.0.dist-info/WHEEL
gerald_tools-0.1.0.dist-info/METADATA
gerald_tools-0.1.0.dist-info/RECORD
